xmlsplit.py
xmlsplit-0.1.2.dist-info/METADATA
xmlsplit-0.1.2.dist-info/WHEEL
xmlsplit-0.1.2.dist-info/entry_points.txt
xmlsplit-0.1.2.dist-info/RECORD
