Metadata-Version: 2.1
Name: xmlsplit
Version: 0.1.2
Summary: split a XML file into pieces
Author: Thiago Curvelo
Author-email: tcurvelo@gmail.com
Requires-Python: >=3.10,<4.0
Classifier: Development Status :: 3 - Alpha
Classifier: Intended Audience :: Developers
Classifier: License :: OSI Approved :: MIT License
Classifier: Programming Language :: Python :: 3
Classifier: Programming Language :: Python :: 3.10
Classifier: Programming Language :: Python :: 3.11
Classifier: Programming Language :: Python :: 3.12
